pyprec/__init__.py
pyprec/export.py
pyprec/pyexporter.py
pyprec/ui.py
pyprec/scripts/__init__.py
pyprec/scripts/pyprec.py
pyprec/templates/CITATION.inc
pyprec/templates/__init__.py
pyprec/templates/configlog.inc
pyprec/templates/initfile.inc
pyprec/templates/main_script.inc
pyprec/templates/pyproject.inc
pyprec/templates/pytest.inc
pyprec/templates/pythonpublish.inc
pyprec/templates/readthedocs.inc
pyprec/templates/setup.inc
pyprec/templates/sphinx/Makefile.new_t
pyprec/templates/sphinx/conf.py_t
pyprec/utils/__init__.py
pyprec/utils/ask_question.py
pyprec/utils/configlog.py
pyprec/utils/utils.py
pyprec-1.0.2.dist-info/LICENSE
pyprec-1.0.2.dist-info/METADATA
pyprec-1.0.2.dist-info/WHEEL
pyprec-1.0.2.dist-info/entry_points.txt
pyprec-1.0.2.dist-info/top_level.txt
pyprec-1.0.2.dist-info/RECORD
