Metadata-Version: 2.1
Name: pyprec
Version: 1.0.2
Summary: Python Package Repository Creator
Home-page: https://github.com/marcorossi5/pyprec.git
Author: M. Rossi
Author-email: marco.rossi@cern.ch
Classifier: Programming Language :: Python :: 3
Classifier: License :: OSI Approved :: MIT License
Classifier: Operating System :: Unix
Requires-Python: >=3.9
License-File: LICENSE
Requires-Dist: six (==1.16.0)
Requires-Dist: pyyaml (==6.0.0)
Requires-Dist: sphinx (>=4.5.0)
Provides-Extra: docs
Requires-Dist: sphinx-rtd-theme (>=1.0.0) ; extra == 'docs'
Requires-Dist: sphinxcontrib-napoleon (>=0.7) ; extra == 'docs'
